st_social_media_links/__init__.py
st_social_media_links/st_social_media_links.py
st_social_media_links-0.1.3.dist-info/LICENSE
st_social_media_links-0.1.3.dist-info/METADATA
st_social_media_links-0.1.3.dist-info/WHEEL
st_social_media_links-0.1.3.dist-info/top_level.txt
st_social_media_links-0.1.3.dist-info/RECORD
