Metadata-Version: 2.1
Name: st-social-media-links
Version: 0.1.3
Summary: A Python package designed to assist in displaying social media links within Streamlit apps.
Home-page: https://github.com/jlnetosci/st_social_media_links
Author: João L. Neto
Keywords: streamlit social media links
Classifier: Programming Language :: Python :: 3
Classifier: License :: OSI Approved :: MIT License
Classifier: Operating System :: OS Independent
Requires-Python: >=3.6
License-File: LICENSE
Requires-Dist: streamlit>=1.32.0
Requires-Dist: beautifulsoup4>=4.12.2
